marl_factory_grid/__init__.py
marl_factory_grid/quickstart.py
marl_factory_grid/algorithms/__init__.py
marl_factory_grid/algorithms/utils.py
marl_factory_grid/algorithms/marl/__init__.py
marl_factory_grid/algorithms/marl/base_ac.py
marl_factory_grid/algorithms/marl/example_config.yaml
marl_factory_grid/algorithms/marl/iac.py
marl_factory_grid/algorithms/marl/mappo.py
marl_factory_grid/algorithms/marl/memory.py
marl_factory_grid/algorithms/marl/networks.py
marl_factory_grid/algorithms/marl/seac.py
marl_factory_grid/algorithms/marl/snac.py
marl_factory_grid/algorithms/static/TSP_base_agent.py
marl_factory_grid/algorithms/static/TSP_dirt_agent.py
marl_factory_grid/algorithms/static/TSP_item_agent.py
marl_factory_grid/algorithms/static/TSP_target_agent.py
marl_factory_grid/algorithms/static/__init__.py
marl_factory_grid/algorithms/static/random_agent.py
marl_factory_grid/algorithms/static/utils.py
marl_factory_grid/configs/_obs_test.yaml
marl_factory_grid/configs/clean_and_bring.yaml
marl_factory_grid/configs/default_config.yaml
marl_factory_grid/configs/eight_puzzle.yaml
marl_factory_grid/configs/narrow_corridor.yaml
marl_factory_grid/configs/two_rooms_one_door.yaml
marl_factory_grid/environment/__init__.py
marl_factory_grid/environment/actions.py
marl_factory_grid/environment/constants.py
marl_factory_grid/environment/factory.py
marl_factory_grid/environment/rewards.py
marl_factory_grid/environment/rules.py
marl_factory_grid/environment/assets/wall.png
marl_factory_grid/environment/assets/agent/adversary.png
marl_factory_grid/environment/assets/agent/agent.png
marl_factory_grid/environment/assets/agent/agent_collision.png
marl_factory_grid/environment/assets/agent/idle.png
marl_factory_grid/environment/assets/agent/invalid.png
marl_factory_grid/environment/assets/agent/move.png
marl_factory_grid/environment/assets/agent/valid.png
marl_factory_grid/environment/entity/__init__.py
marl_factory_grid/environment/entity/agent.py
Marl_Factory_Grid-0.2.5.dist-info/METADATA
Marl_Factory_Grid-0.2.5.dist-info/WHEEL
Marl_Factory_Grid-0.2.5.dist-info/top_level.txt
Marl_Factory_Grid-0.2.5.dist-info/RECORD
