Metadata-Version: 2.1
Name: Marl-Factory-Grid
Version: 0.2.5
Summary: A framework to research MARL agents in various setings.
Home-page: https://github.com/illiumst/marl-factory-grid/import
Author: Steffen Illium
Author-email: steffen.illium@ifi.lmu.de
License: MIT
Keywords: artificial intelligence,pytorch,multiagent reinforcement learning,simulation,emergence,gymnasium,environment,deepdiff,natsort
Classifier: Development Status :: 4 - Beta
Classifier: Intended Audience :: Developers
Classifier: Topic :: Scientific/Engineering :: Artificial Intelligence
Classifier: License :: OSI Approved :: MIT License
Classifier: Programming Language :: Python :: 3.11
Requires-Dist: numpy
Requires-Dist: pygame (>=2.0)
Requires-Dist: numba (>=0.56)
Requires-Dist: gymnasium (>=0.26)
Requires-Dist: seaborn
Requires-Dist: pandas
Requires-Dist: pyyaml
Requires-Dist: networkx
Requires-Dist: torch
Requires-Dist: tqdm
